lqlpath/__init__.py
lqlpath/bq_res_name_value.py
lqlpath/functions.py
lqlpath/data/bigquery_dataset.txt
lqlpath/data/bigquery_project.txt
lqlpath/data/bigquery_resource.txt
lqlpath/data/bigquery_table.txt
lqlpath-0.2.0.dist-info/METADATA
lqlpath-0.2.0.dist-info/WHEEL
lqlpath-0.2.0.dist-info/top_level.txt
lqlpath-0.2.0.dist-info/RECORD
