Metadata-Version: 2.1
Name: lqlpath
Version: 0.2.0
Summary: A package for searching log query language path 
Author: Harish Lohiya
Author-email: harishlohiya@gmail.com
Classifier: Programming Language :: Python :: 2.7
Classifier: License :: OSI Approved :: MIT License
Classifier: Operating System :: OS Independent
Requires-Python: >=2.7
